setup.py
persistentlist/__init__.py
persistentlist.egg-info/PKG-INFO
persistentlist.egg-info/SOURCES.txt
persistentlist.egg-info/dependency_links.txt
persistentlist.egg-info/top_level.txt