Metadata-Version: 1.1
Name: persistentlist
Version: 0.4
Summary: library providing a persistent list of n object
Home-page: https://github.com/chaica/persistentlist
Author: Carl Chenet
Author-email: chaica@ohmytux.com
License: GNU GPL v3
Download-URL: https://github.com/chaica/persistentlist
Platform: UNKNOWN
Classifier: Intended Audience :: Developers
Classifier: Environment :: Console
Classifier: License :: OSI Approved :: GNU General Public License (GPL)
Classifier: Operating System :: POSIX :: Linux
Classifier: Programming Language :: Python :: 3.5
